latexit-0.2.0.dist-info/licenses/LICENSE
src/__init__.py
src/__main__.py
src/cli.py
latexit-0.2.0.dist-info/METADATA
latexit-0.2.0.dist-info/WHEEL
latexit-0.2.0.dist-info/entry_points.txt
latexit-0.2.0.dist-info/top_level.txt
latexit-0.2.0.dist-info/RECORD
